[
    {
        "model": "idb.image",
        "pk": 1,
        "fields": {
            "description": "Testing",
            "link": "http://i.walmartimages.com/i/p/00/04/54/96/88/0004549688085_500X500.jpg"
        }
    },
    {
        "model": "idb.image",
        "pk": 2,
        "fields": {
            "description": "Testing",
            "link": "http://nonspecificaction.co.uk/wp-content/uploads/Wii-U-Black.jpg"
        }
    },
    {
        "model": "idb.image",
        "pk": 3,
        "fields": {
            "description": "Testing",
            "link": "http://pisces.bbystatic.com/image2/BestBuy_US/images/products/6775/6775792_sa.jpg"
        }
    },
    {
        "model": "idb.image",
        "pk": 4,
        "fields": {
            "description": "Testing",
            "link": "http://nonspecificaction.co.uk/wp-content/uploads/platinum-games-logo.jpg"
        }
    },
    {
        "model": "idb.image",
        "pk": 5,
        "fields": {
            "description": "Testing",
            "link": "http://www.gamechup.com/wp-content/uploads/2014/01/platinum-games-project-nagano.jpg"
        }
    },
    {
        "model": "idb.image",
        "pk": 6,
        "fields": {
            "description": "Testing",
            "link": "http://3.bp.blogspot.com/_Z50Ik1LwTlQ/TUAHdjb-3oI/AAAAAAAAEYA/pj5C9fp1ctg/s1600/platgamesega.jpg"
        }
    },
    {
        "model": "idb.image",
        "pk": 7,
        "fields": {
            "description": "Testing",
            "link": "http://s11.postimg.org/xjy2jtm6b/the_wonderful_101_logo.png"
        }
    },
    {
        "model": "idb.image",
        "pk": 8,
        "fields": {
            "description": "Testing",
            "link": "http://venturebeat.files.wordpress.com/2013/05/the-wonderful-101.jpg"
        }
    },
    {
        "model": "idb.image",
        "pk": 9,
        "fields": {
            "description": "Testing",
            "link": "http://stickskills.com/wp-content/uploads/2013/01/The-Wonderful-101.jpg"
        }
    },
    {
        "model": "idb.platform",
        "pk": 1,
        "fields": {
            "name": "Wii U",
            "manufacturer": "Nintendo",
            "release_date": "2012-11-18",
            "media_format": "Physical (disks) and digital",
            "generation": 8,
            "youtube_link": "www.youtube.com/embed/qhlDHeCT-Q8",
            "twitter_link": "446085251077373952",
            "images": [1, 2, 3]
        }
    },
    {
        "model": "idb.developer",
        "pk": 1,
        "fields": {
            "name": "Platinum Games",
            "date_founded": "2006-04-08",
            "num_employees": 120,
            "status": "Active",
            "address": "Umeda Sky Building Tower West 8F,\n1-1-30 Oyodo-naka, Kita-ku, Osaka, 531-6108",
            "map_link": "https://maps.google.com/maps?f=q&source=s_q&hl=en&geocode=&q=1-1-30+Oyodo-naka,+Kita-ku,+Osaka,+531-6108&aq=&sll=34.704426,135.485297&sspn=0.004397,0.008256&ie=UTF8&hq=&hnear=1+Chome-1-30+%C5%8Cyodonaka,+Kita-ku,+%C5%8Csaka-shi,+%C5%8Csaka-fu,+Japan&ll=34.70533,135.489699&spn=0.035033,0.066047&t=m&z=14&output=embed",
            "images": [4, 5, 6],
            "platforms": [1]
        }
    },
    {
        "model": "idb.game",
        "pk": 1,
        "fields": {
            "title": "The Wonderful 101",
            "release_date": "2013-09-15",
            "genre": "Action",
            "publisher": "Nintendo",
            "ESRB_rating": "T",
            "youtube_link": "www.youtube.com/embed/z9ueBmNNGus",
            "images": [7, 8, 9],
            "developer": 1, 
            "platforms":[1]
        }
    }
]